{
  "semesters": {
    "1": {
      "subjects": ["C Programming", "Maths"],
      "problems": {
        "C Programming": [
          {
            "title": "Hello World",
            "code": "#include<stdio.h>\nint main(){ printf(\"Hello World\"); return 0; }",
            "output": "Hello World"
          },
          {
            "title": "Sum of Two Numbers",
            "code": "#include<stdio.h>\nint main(){ int a=5,b=3; printf(\"%d\",a+b); return 0; }",
            "output": "8"
          }
        ],
        "Maths": [
          {
            "title": "Factorial",
            "code": "#include<stdio.h>\nint main(){ int n=5,f=1; for(int i=1;i<=n;i++) f*=i; printf(\"%d\",f); return 0; }",
            "output": "120"
          }
        ]
      }
    },

    "2": {
      "subjects": ["C++"],
      "problems": {
        "C++": [
          {
            "title": "OOP Example",
            "code": "#include<iostream>\nusing namespace std;\nclass Test{ public: void show(){ cout<<\"Hello\"; } }; int main(){ Test t; t.show(); return 0; }",
            "output": "Hello"
          }
        ]
      }
    },

    "3": {
      "subjects": ["digital Electronics"],
      "problems": {
        "digital Electronics": [
          {
            "title": "AND Gate",
            "code": "#include<iostream>\nusing namespace std;\nclass Test{ public: void show(){ cout<<\"Hello\"; } }; int main(){ Test t; t.show(); return 0; }",
            "output": "Hello"
          }
        ]
      }
    }




    
  }
}
